witwidget/__init__.py
witwidget/version.py
witwidget/_utils/__init__.py
witwidget/_utils/common_utils.py
witwidget/_utils/inference_utils.py
witwidget/_utils/platform_utils.py
witwidget/_vendor/__init__.py
witwidget/_vendor/tensorflow_serving/__init__.py
witwidget/_vendor/tensorflow_serving/apis/__init__.py
witwidget/_vendor/tensorflow_serving/apis/classification_pb2.py
witwidget/_vendor/tensorflow_serving/apis/get_model_metadata_pb2.py
witwidget/_vendor/tensorflow_serving/apis/get_model_status_pb2.py
witwidget/_vendor/tensorflow_serving/apis/inference_pb2.py
witwidget/_vendor/tensorflow_serving/apis/input_pb2.py
witwidget/_vendor/tensorflow_serving/apis/model_management_pb2.py
witwidget/_vendor/tensorflow_serving/apis/model_pb2.py
witwidget/_vendor/tensorflow_serving/apis/model_service_pb2.py
witwidget/_vendor/tensorflow_serving/apis/model_service_pb2_grpc.py
witwidget/_vendor/tensorflow_serving/apis/predict_pb2.py
witwidget/_vendor/tensorflow_serving/apis/prediction_log_pb2.py
witwidget/_vendor/tensorflow_serving/apis/prediction_service_pb2.py
witwidget/_vendor/tensorflow_serving/apis/prediction_service_pb2_grpc.py
witwidget/_vendor/tensorflow_serving/apis/regression_pb2.py
witwidget/_vendor/tensorflow_serving/apis/session_service_pb2.py
witwidget/_vendor/tensorflow_serving/config/__init__.py
witwidget/_vendor/tensorflow_serving/config/log_collector_config_pb2.py
witwidget/_vendor/tensorflow_serving/config/logging_config_pb2.py
witwidget/_vendor/tensorflow_serving/config/model_server_config_pb2.py
witwidget/_vendor/tensorflow_serving/sources/__init__.py
witwidget/_vendor/tensorflow_serving/sources/storage_path/__init__.py
witwidget/_vendor/tensorflow_serving/sources/storage_path/file_system_storage_path_source_pb2.py
witwidget/_vendor/tensorflow_serving/util/__init__.py
witwidget/_vendor/tensorflow_serving/util/status_pb2.py
witwidget/notebook/__init__.py
witwidget/notebook/base.py
witwidget/notebook/visualization.py
witwidget/notebook/colab/__init__.py
witwidget_gpu-1.6.0.dist-info/METADATA
witwidget_gpu-1.6.0.dist-info/WHEEL
witwidget_gpu-1.6.0.dist-info/top_level.txt
witwidget_gpu-1.6.0.dist-info/RECORD
