Metadata-Version: 2.1
Name: witwidget-gpu
Version: 1.6.0
Summary: What-If Tool jupyter widget
Home-page: https://github.com/pair-code/what-if-tool
Author: Google Inc.
Author-email: packages@tensorflow.org
License: Apache 2.0
Keywords: ipython,jupyter,widgets
Platform: UNKNOWN
Classifier: Development Status :: 4 - Beta
Classifier: Framework :: IPython
Classifier: Intended Audience :: Developers
Classifier: Intended Audience :: Science/Research
Classifier: Topic :: Multimedia :: Graphics
Classifier: Programming Language :: Python :: 2
Classifier: Programming Language :: Python :: 2.7
Classifier: Programming Language :: Python :: 3
Classifier: Programming Language :: Python :: 3.3
Classifier: Programming Language :: Python :: 3.4
Classifier: Programming Language :: Python :: 3.5
Classifier: Programming Language :: Python :: 3.6
Requires-Dist: absl-py (>=0.4)
Requires-Dist: google-api-python-client (>=1.7.8)
Requires-Dist: ipywidgets (>=7.0.0)
Requires-Dist: jupyter (<2,>=1.0)
Requires-Dist: oauth2client (>=4.1.3)
Requires-Dist: six (>=1.12.0)
Requires-Dist: tensorflow-gpu (>=1.12.0)
